xboto/__init__.py
xboto/client.py
xboto/dependencies.py
xboto/resource.py
xboto-1.1.1.dist-info/LICENSE
xboto-1.1.1.dist-info/METADATA
xboto-1.1.1.dist-info/WHEEL
xboto-1.1.1.dist-info/RECORD
