Metadata-Version: 2.1
Name: xboto
Version: 1.1.1
Summary: Easy lazy dependency injection for boto3 clients/resources.
Home-page: https://github.com/xyngular/py-xboto
Keywords: boto,boto client,boto resource,inject,lazy,dependency,dependency injection,aws
Author: Josh Orr
Author-email: josh@orr.blue
Requires-Python: >=3.8,<4.0
Classifier: License :: OSI Approved :: The Unlicense (Unlicense)
Classifier: Programming Language :: Python :: 3
Classifier: Programming Language :: Python :: 3.8
Classifier: Programming Language :: Python :: 3.9
Classifier: Programming Language :: Python :: 3.10
Classifier: Programming Language :: Python :: 3.11
Classifier: Topic :: Software Development :: Libraries :: Python Modules
Requires-Dist: boto3 (>=1.26.64,<2.0.0)
Requires-Dist: botocore (>=1.29.64,<2.0.0)
Requires-Dist: xinject (>=1.4.0,<2.0.0)
Requires-Dist: xsentinels (>=1.2.1,<2.0.0)
Project-URL: Repository, https://github.com/xyngular/py-xboto
